gitv/__init__.py
gitv/git_version.py
gitv/plugins/__init__.py
gitv/plugins/hatch.py
gitv/plugins/poetry.py
gitv/plugins/setup.py
gitv-2.2.2.dist-info/LICENSE
gitv-2.2.2.dist-info/METADATA
gitv-2.2.2.dist-info/WHEEL
gitv-2.2.2.dist-info/entry_points.txt
gitv-2.2.2.dist-info/top_level.txt
gitv-2.2.2.dist-info/RECORD
