Metadata-Version: 2.1
Name: gitv
Version: 2.2.2
Summary: A biased Git versioning tool for Python project.
Home-page: https://github.com/figroc/py-gitv
Author: figroc
License: MIT
Requires-Python: >=3.8
License-File: LICENSE
Provides-Extra: hatch
Requires-Dist: hatch ; extra == 'hatch'
Provides-Extra: poetry
Requires-Dist: poetry ; extra == 'poetry'
